chewy_attachment/__init__.py
chewy_attachment/core/__init__.py
chewy_attachment/core/exceptions.py
chewy_attachment/core/permissions.py
chewy_attachment/core/schemas.py
chewy_attachment/core/storage.py
chewy_attachment/core/utils.py
chewy_attachment/django_app/__init__.py
chewy_attachment/django_app/admin.py
chewy_attachment/django_app/apps.py
chewy_attachment/django_app/models.py
chewy_attachment/django_app/permissions.py
chewy_attachment/django_app/serializers.py
chewy_attachment/django_app/urls.py
chewy_attachment/django_app/views.py
chewy_attachment/django_app/migrations/0001_initial.py
chewy_attachment/django_app/migrations/__init__.py
chewy_attachment/django_app/tests/__init__.py
chewy_attachment/django_app/tests/conftest.py
chewy_attachment/django_app/tests/test_views.py
chewy_attachment/fastapi_app/__init__.py
chewy_attachment/fastapi_app/crud.py
chewy_attachment/fastapi_app/dependencies.py
chewy_attachment/fastapi_app/models.py
chewy_attachment/fastapi_app/router.py
chewy_attachment/fastapi_app/schemas.py
chewy_attachment/fastapi_app/tests/__init__.py
chewy_attachment/fastapi_app/tests/conftest.py
chewy_attachment/fastapi_app/tests/test_router.py
chewy_attachment-0.4.3.dist-info/METADATA
chewy_attachment-0.4.3.dist-info/WHEEL
chewy_attachment-0.4.3.dist-info/licenses/LICENSE
chewy_attachment-0.4.3.dist-info/RECORD
