Metadata-Version: 2.4
Name: chewy-attachment
Version: 0.4.3
Summary: 通用图片/附件管理插件，支持 Django 和 FastAPI
Project-URL: Homepage, https://github.com/cone387/ChewyAttachment
Project-URL: Repository, https://github.com/cone387/ChewyAttachment
Project-URL: Issues, https://github.com/cone387/ChewyAttachment/issues
Project-URL: Documentation, https://github.com/cone387/ChewyAttachment#readme
Author-email: cone387 <cone387@gmail.com>
Maintainer-email: cone387 <cone387@gmail.com>
License: MIT
License-File: LICENSE
Keywords: attachment,django,fastapi,file-management,file-upload,image-upload
Classifier: Development Status :: 4 - Beta
Classifier: Framework :: Django
Classifier: Framework :: Django :: 4.0
Classifier: Framework :: Django :: 5.0
Classifier: Framework :: FastAPI
Classifier: Intended Audience :: Developers
Classifier: License :: OSI Approved :: MIT License
Classifier: Programming Language :: Python :: 3
Classifier: Programming Language :: Python :: 3.9
Classifier: Programming Language :: Python :: 3.10
Classifier: Programming Language :: Python :: 3.11
Classifier: Programming Language :: Python :: 3.12
Classifier: Programming Language :: Python :: 3.13
Classifier: Topic :: Internet :: WWW/HTTP
Classifier: Topic :: Software Development :: Libraries :: Python Modules
Requires-Python: >=3.9
Requires-Dist: python-magic>=0.4.27
Provides-Extra: dev
Requires-Dist: django>=4.2.0; extra == 'dev'
Requires-Dist: djangorestframework>=3.14.0; extra == 'dev'
Requires-Dist: fastapi>=0.109.0; extra == 'dev'
Requires-Dist: httpx>=0.26.0; extra == 'dev'
Requires-Dist: pytest-asyncio>=0.23.0; extra == 'dev'
Requires-Dist: pytest-cov>=4.1.0; extra == 'dev'
Requires-Dist: pytest-django>=4.7.0; extra == 'dev'
Requires-Dist: pytest>=8.0.0; extra == 'dev'
Requires-Dist: python-multipart>=0.0.6; extra == 'dev'
Requires-Dist: ruff>=0.1.0; extra == 'dev'
Requires-Dist: sqlmodel>=0.0.14; extra == 'dev'
Requires-Dist: uvicorn>=0.27.0; extra == 'dev'
Provides-Extra: django
Requires-Dist: django>=4.2.0; extra == 'django'
Requires-Dist: djangorestframework>=3.14.0; extra == 'django'
Provides-Extra: fastapi
Requires-Dist: fastapi>=0.109.0; extra == 'fastapi'
Requires-Dist: python-multipart>=0.0.6; extra == 'fastapi'
Requires-Dist: sqlmodel>=0.0.14; extra == 'fastapi'
Requires-Dist: uvicorn>=0.27.0; extra == 'fastapi'
Provides-Extra: test
Requires-Dist: httpx>=0.26.0; extra == 'test'
Requires-Dist: pytest-asyncio>=0.23.0; extra == 'test'
Requires-Dist: pytest-cov>=4.1.0; extra == 'test'
Requires-Dist: pytest>=8.0.0; extra == 'test'
Provides-Extra: test-django
Requires-Dist: django>=4.2.0; extra == 'test-django'
Requires-Dist: djangorestframework>=3.14.0; extra == 'test-django'
Requires-Dist: httpx>=0.26.0; extra == 'test-django'
Requires-Dist: pytest-asyncio>=0.23.0; extra == 'test-django'
Requires-Dist: pytest-cov>=4.1.0; extra == 'test-django'
Requires-Dist: pytest-django>=4.7.0; extra == 'test-django'
Requires-Dist: pytest>=8.0.0; extra == 'test-django'
Provides-Extra: test-fastapi
Requires-Dist: fastapi>=0.109.0; extra == 'test-fastapi'
Requires-Dist: httpx>=0.26.0; extra == 'test-fastapi'
Requires-Dist: pytest-asyncio>=0.23.0; extra == 'test-fastapi'
Requires-Dist: pytest-cov>=4.1.0; extra == 'test-fastapi'
Requires-Dist: pytest>=8.0.0; extra == 'test-fastapi'
Requires-Dist: python-multipart>=0.0.6; extra == 'test-fastapi'
Requires-Dist: sqlmodel>=0.0.14; extra == 'test-fastapi'
Requires-Dist: uvicorn>=0.27.0; extra == 'test-fastapi'
